llama_tools_jaliya/__init__.py
llama_tools_jaliya/__main__.py
llama_tools_jaliya/convert_and_quantize.py
llama_tools_jaliya/push_gguf.py
llama_tools_jaliya/server.py
llama_tools_jaliya/setup.py
llama_tools_jaliya/setup_llama_cpp.py
llama_tools_jaliya/utils.py
llama_tools_jaliya/venv.py
llama_tools_jaliya-0.1.3.dist-info/METADATA
llama_tools_jaliya-0.1.3.dist-info/WHEEL
llama_tools_jaliya-0.1.3.dist-info/entry_points.txt
llama_tools_jaliya-0.1.3.dist-info/top_level.txt
llama_tools_jaliya-0.1.3.dist-info/RECORD
